mandaw/__init__.py
mandaw/animation.py
mandaw/audio.py
mandaw/color.py
mandaw/entity.py
mandaw/input.py
mandaw/main.py
mandaw/sprite.py
mandaw/text.py
mandaw-2.3.0.dist-info/LICENSE
mandaw-2.3.0.dist-info/METADATA
mandaw-2.3.0.dist-info/WHEEL
mandaw-2.3.0.dist-info/top_level.txt
mandaw-2.3.0.dist-info/RECORD
