Metadata-Version: 2.1
Name: mandaw
Version: 2.3.0
Summary: A 2D GameEngine Made In Python With PySDL2
Home-page: https://mandaw2014.github.io/MandawEngineSDL/
Author: mandaw2014
Author-email: mandawbuisness@gmail.com
License: UNKNOWN
Platform: UNKNOWN
Requires-Python: >=3.6
License-File: LICENSE
Requires-Dist: pysdl2
Requires-Dist: pysdl2-dll
